{
    "chat_id": "vsr-r_g6CrGpCRu5AAAF",
    "ticket_id": "SVC-14716",
    "user": "admin",
    "history": {
        "1": {
            "recipient": "wl_vertex",
            "time": "2024-10-16T20:48:43.680159",
            "message": "Hello! How can I help you today?"
        },
        "2": {
            "recipient": "admin",
            "time": "2024-10-16T20:48:53.529986",
            "message": "Hello, I am having trouble logging into webgui, can you check the logs ?",
            "attachment": {
                "0": {
                    "filename": "log.txt",
                    "path": "./bucket/chats/admin\\vsr-r_g6CrGpCRu5AAAF\\vsr-r_g6CrGpCRu5AAAF\\log.txt",
                    "extension": "txt",
                    "mime_type": "text/plain",
                    "size": 4382
                },
                "1": {
                    "filename": "Invalid_LoginID.jpg",
                    "path": "./bucket/chats/admin\\vsr-r_g6CrGpCRu5AAAF\\vsr-r_g6CrGpCRu5AAAF\\Invalid_LoginID.jpg",
                    "extension": "jpg",
                    "mime_type": "image/jpeg",
                    "size": 31031
                }
            }
        },
        "3": {
            "recipient": "wl_vertex",
            "time": "2024-10-16T20:48:59.167025",
            "message": "Hello! I see you are having trouble logging into WebGUI. I'm analyzing the provided logs. Just a moment.\n\nOkay, I've gone through the logs. It appears there were multiple attempts to create and delete employee entries and courses.  Later, the logs show \"Invalid username or password !\" repeated three times, followed by a \"Database Reset\" message. This indicates the login issue might be due to incorrect credentials or a recent database reset affecting your account.\n\nCan you please confirm if you are using the correct username and password? If you are sure about your credentials,  we might need to investigate the database reset further.\n\nType 'create' to create a ticket, or 'status' to see the current status and analysis."
        },
        "4": {
            "recipient": "admin",
            "time": "2024-10-16T20:49:01.256154",
            "message": "/create"
        },
        "5": {
            "recipient": "wl_vertex",
            "time": "2024-10-16T20:49:12.214685",
            "message": "I've analyzed the logs you provided. It seems there were multiple attempts to create and delete employee entries and courses, followed by repeated \"Invalid username or password!\" errors and a \"Database Reset\" message. This indicates the login issue might be due to incorrect credentials or a recent database reset affecting your account.\n\nCan you please confirm if you are using the correct username and password? If you are sure about your credentials, we might need to investigate the database reset further."
        }
    },
    "closed_chat": {
        "chat_id": "vsr-r_g6CrGpCRu5AAAF",
        "ticket_id": "SVC-14716",
        "user": "admin",
        "description": "User is unable to log into WebGUI. Provided logs indicate multiple attempts to create and delete employee entries and courses, followed by repeated \"Invalid username or password!\" errors and a \"Database Reset\" message.  This suggests potential incorrect credentials or a database reset affecting the account.",
        "medium": "",
        "connection": "closed",
        "text": "",
        "subject": "WebGUI Login Issue",
        "summary": "User experiencing WebGUI login problems. Logs show failed login attempts, database reset, and possible credential issues.",
        "attachments": [
            {
                "filename": "log.txt",
                "path": "./bucket/chats/admin\\vsr-r_g6CrGpCRu5AAAF\\vsr-r_g6CrGpCRu5AAAF\\log.txt",
                "extension": "txt",
                "mime_type": "text/plain",
                "size": 4382
            },
            {
                "filename": "Invalid_LoginID.jpg",
                "path": "./bucket/chats/admin\\vsr-r_g6CrGpCRu5AAAF\\vsr-r_g6CrGpCRu5AAAF\\Invalid_LoginID.jpg",
                "extension": "jpg",
                "mime_type": "image/jpeg",
                "size": 31031
            }
        ],
        "product_type": "webgui",
        "issue_type": "error",
        "priority": "medium",
        "story_points": "3",
        "estimation": "4",
        "analysis": "The login issue could be due to incorrect credentials or a recent database reset. If the user is certain about their credentials, further investigation into the database reset is needed.  Check database integrity, restore from backup if necessary, or reset the user's password if compromised.",
        "reply": "I've analyzed the logs you provided. It seems there were multiple attempts to create and delete employee entries and courses, followed by repeated \"Invalid username or password!\" errors and a \"Database Reset\" message. This indicates the login issue might be due to incorrect credentials or a recent database reset affecting your account.\n\nCan you please confirm if you are using the correct username and password? If you are sure about your credentials, we might need to investigate the database reset further.",
        "created": "2024-10-16T20:49:12.214685",
        "updated": "2024-10-16T20:49:12.214685"
    }
}